{
  "version": 1,
  "base_track": "гѓ«гѓјгѓ—г‚№гѓ”гѓЉ",
  "base_artist": "зЁІи‘‰ж›‡",
  "createdAt": "2026-03-10T15:41:38.445613Z",
  "candidates": [
    {
      "id": "lrclib_1",
      "source": "lrclib",
      "title": "гѓ«гѓјгѓ—г‚№гѓ”гѓЉ",
      "artist": "зЁІи‘‰ж›‡",
      "has_synced": true,
      "path": "select/01_гѓ«гѓјгѓ—г‚№гѓ”гѓЉ_зЁІи‘‰ж›‡.lrc"
    },
    {
      "id": "petitlyrics_1",
      "source": "petitlyrics",
      "title": "гѓ«гѓјгѓ—г‚№гѓ”гѓЉ",
      "artist": "зЁІи‘‰ж›‡",
      "has_synced": false,
      "path": "select/pl_01_гѓ«гѓјгѓ—г‚№гѓ”гѓЉ_зЁІи‘‰ж›‡.txt"
    }
  ]
}